pyterrier_adaptive/__init__.py
pyterrier_adaptive/_laff.py
pyterrier_adaptive/corpus_graph.py
pyterrier_adaptive/gar.py
pyterrier_adaptive/pt_docs/index.rst
pyterrier_adaptive-0.2.0.dist-info/LICENSE
pyterrier_adaptive-0.2.0.dist-info/METADATA
pyterrier_adaptive-0.2.0.dist-info/WHEEL
pyterrier_adaptive-0.2.0.dist-info/entry_points.txt
pyterrier_adaptive-0.2.0.dist-info/top_level.txt
pyterrier_adaptive-0.2.0.dist-info/RECORD
