Metadata-Version: 2.1
Name: pyterrier-adaptive
Version: 0.2.0
Summary: PyTerrier implementation of Adaptive Re-Ranking using a Corpus Graph (CIKM 2022)
Author-email: Sean MacAvaney <sean.macavaney@glasgow.ac.uk>
Maintainer-email: Sean MacAvaney <sean.macavaney@glasgow.ac.uk>
Project-URL: Repository, https://github.com/terrierteam/pyterrier_adaptive
Project-URL: Bug Tracker, https://github.com/terrierteam/pyterrier_adaptive/issues
Classifier: Programming Language :: Python
Classifier: Operating System :: OS Independent
Classifier: Topic :: Text Processing
Classifier: Topic :: Text Processing :: Indexing
Classifier: License :: OSI Approved :: MIT License
Requires-Python: >=3.8
License-File: LICENSE
Requires-Dist: python-terrier
Requires-Dist: npids>=0.0.2
Requires-Dist: pyterrier-alpha>=0.6.2
Requires-Dist: torch
Requires-Dist: pandas
Requires-Dist: tqdm
Requires-Dist: more_itertools
Provides-Extra: laff
Requires-Dist: transformers; extra == "laff"
